knx_stack/__init__.py
knx_stack/address.py
knx_stack/datapointtypes.py
knx_stack/msg.py
knx_stack/state.py
knx_stack/client/__init__.py
knx_stack/client/knxnet_ip.py
knx_stack/client/knxnet_ip_discovery.py
knx_stack/client/usbhid.py
knx_stack/decode/__init__.py
knx_stack/decode/cemi/__init__.py
knx_stack/decode/cemi/emi_id.py
knx_stack/decode/cemi/msg_code.py
knx_stack/decode/cemi/ldata/__init__.py
knx_stack/decode/cemi/ldata/con.py
knx_stack/decode/cemi/ldata/ind.py
knx_stack/decode/knxnet_ip/__init__.py
knx_stack/decode/knxnet_ip/header.py
knx_stack/decode/knxnet_ip/core/__init__.py
knx_stack/decode/knxnet_ip/core/connect/__init__.py
knx_stack/decode/knxnet_ip/core/connect/res.py
knx_stack/decode/knxnet_ip/core/connectionstate/__init__.py
knx_stack/decode/knxnet_ip/core/connectionstate/res.py
knx_stack/decode/knxnet_ip/core/disconnect/__init__.py
knx_stack/decode/knxnet_ip/core/disconnect/res.py
knx_stack/decode/knxnet_ip/core/search/__init__.py
knx_stack/decode/knxnet_ip/core/search/res.py
knx_stack/decode/knxnet_ip/tunneling/__init__.py
knx_stack/decode/knxnet_ip/tunneling/ack.py
knx_stack/decode/knxnet_ip/tunneling/req.py
knx_stack/decode/layer/__init__.py
knx_stack/decode/layer/application/__init__.py
knx_stack/decode/layer/application/a_group_value.py
knx_stack/decode/layer/application/a_property_value.py
knx_stack/decode/layer/application/a_group_value_read/__init__.py
knx_stack/decode/layer/application/a_group_value_read/con.py
knx_stack/decode/layer/application/a_group_value_read/ind.py
knx_stack/decode/layer/application/a_group_value_response/__init__.py
knx_stack/decode/layer/application/a_group_value_response/con.py
knx_stack/decode/layer/application/a_group_value_response/ind.py
knx_stack/decode/layer/application/a_group_value_write/__init__.py
knx_stack/decode/layer/application/a_group_value_write/con.py
knx_stack/decode/layer/application/a_group_value_write/ind.py
knx_stack/decode/layer/application/a_property_value_read/__init__.py
knx_stack-0.9.2.dist-info/COPYING
knx_stack-0.9.2.dist-info/METADATA
knx_stack-0.9.2.dist-info/WHEEL
knx_stack-0.9.2.dist-info/top_level.txt
knx_stack-0.9.2.dist-info/RECORD
