Metadata-Version: 2.1
Name: knx-stack
Version: 0.9.2
Summary: A python3 KNX stack for USB HID and KNXnet IP
Home-page: https://github.com/majamassarini/knx-stack
Author: Maja Massarini
Author-email: maja.massarini@gmail.com
License: MIT
Platform: UNKNOWN
Classifier: Development Status :: 3 - Alpha
Classifier: License :: OSI Approved :: MIT License
Classifier: Operating System :: POSIX :: Linux
Classifier: Programming Language :: Python :: 3.8
Classifier: Topic :: Communications
Classifier: Intended Audience :: Developers
License-File: COPYING
